agentfive_middleware/__init__.py
agentfive_middleware/middleware.py
scrapy_agentfive_middleware-0.0.2.dist-info/LICENSE.txt
scrapy_agentfive_middleware-0.0.2.dist-info/METADATA
scrapy_agentfive_middleware-0.0.2.dist-info/WHEEL
scrapy_agentfive_middleware-0.0.2.dist-info/top_level.txt
scrapy_agentfive_middleware-0.0.2.dist-info/RECORD
