Metadata-Version: 2.1
Name: scrapy-agentfive-middleware
Version: 0.0.2
Summary: Scrapy downloader middleware to interact with agentfive API
Home-page: https://github.com/agentfivecn/scrapy-agentfive-middleware
Author: agentfive
Author-email: service@agentfive.cn
License: MIT
Platform: UNKNOWN
Classifier: Development Status :: 1 - Planning
Classifier: License :: OSI Approved :: MIT License
Classifier: Programming Language :: Python
Classifier: Programming Language :: Python :: 3.5
Classifier: Programming Language :: Python :: 3.6
Classifier: Programming Language :: Python :: 3.7
Classifier: Programming Language :: Python :: 3.8
Classifier: Framework :: Scrapy
Classifier: Intended Audience :: Developers
Classifier: Topic :: Internet :: WWW/HTTP
Classifier: Topic :: Software Development :: Libraries :: Application Frameworks
Classifier: Topic :: Software Development :: Libraries :: Python Modules
Requires-Python: >=3.5
Requires-Dist: scrapy (>=1.6.0)
